{
  "287": {
    "document_frequencies": {
      "0": 1.0
    },
    "field_frequencies": {
      "0": {
        "text": 1
      }
    },
    "positions": {
      "0": [
        560
      ]
    },
    "idf": 2.5902671654458267,
    "total_frequency": 1
  },
  "31": {
    "document_frequencies": {
      "0": 1.0
    },
    "field_frequencies": {
      "0": {
        "text": 1
      }
    },
    "positions": {
      "0": [
        569
      ]
    },
    "idf": 2.5902671654458267,
    "total_frequency": 1
  },
  "543": {
    "document_frequencies": {
      "1": 1.0
    },
    "field_frequencies": {
      "1": {
        "text": 1
      }
    },
    "positions": {
      "1": [
        184
      ]
    },
    "idf": 2.5902671654458267,
    "total_frequency": 1
  },
  "799": {
    "document_frequencies": {
      "4": 1.0,
      "7": 1.0,
      "13": 1.0
    },
    "field_frequencies": {
      "4": {
        "text": 1
      },
      "7": {
        "text": 1
      },
      "13": {
        "text": 1
      }
    },
    "positions": {
      "4": [
        63
      ],
      "7": [
        507
      ],
      "13": [
        187
      ]
    },
    "idf": 1.742969305058623,
    "total_frequency": 3
  },
  "1055": {
    "document_frequencies": {
      "5": 1.0,
      "15": 1.0,
      "18": 1.0
    },
    "field_frequencies": {
      "5": {
        "text": 1
      },
      "15": {
        "text": 1
      },
      "18": {
        "text": 1
      }
    },
    "positions": {
      "5": [
        324
      ],
      "15": [
        61
      ],
      "18": [
        318
      ]
    },
    "idf": 1.742969305058623,
    "total_frequency": 3
  },
  "1311": {
    "document_frequencies": {
      "6": 1.0
    },
    "field_frequencies": {
      "6": {
        "text": 1
      }
    },
    "positions": {
      "6": [
        579
      ]
    },
    "idf": 2.5902671654458267,
    "total_frequency": 1
  },
  "1567": {
    "document_frequencies": {
      "7": 2.0
    },
    "field_frequencies": {
      "7": {
        "text": 2
      }
    },
    "positions": {
      "7": [
        187,
        520
      ]
    },
    "idf": 2.5902671654458267,
    "total_frequency": 2
  },
  "1823": {
    "document_frequencies": {
      "8": 1.0
    },
    "field_frequencies": {
      "8": {
        "text": 1
      }
    },
    "positions": {
      "8": [
        307
      ]
    },
    "idf": 2.5902671654458267,
    "total_frequency": 1
  },
  "2079": {
    "document_frequencies": {
      "10": 1.0
    },
    "field_frequencies": {
      "10": {
        "text": 1
      }
    },
    "positions": {
      "10": [
        632
      ]
    },
    "idf": 2.5902671654458267,
    "total_frequency": 1
  },
  "2335": {
    "document_frequencies": {
      "11": 1.0,
      "13": 2.0,
      "15": 2.0
    },
    "field_frequencies": {
      "11": {
        "text": 1
      },
      "13": {
        "text": 2
      },
      "15": {
        "text": 2
      }
    },
    "positions": {
      "11": [
        224
      ],
      "13": [
        13,
        18
      ],
      "15": [
        160,
        166
      ]
    },
    "idf": 1.742969305058623,
    "total_frequency": 5
  },
  "2591": {
    "document_frequencies": {
      "12": 1.0
    },
    "field_frequencies": {
      "12": {
        "text": 1
      }
    },
    "positions": {
      "12": [
        110
      ]
    },
    "idf": 2.5902671654458267,
    "total_frequency": 1
  },
  "2847": {
    "document_frequencies": {
      "15": 1.0
    },
    "field_frequencies": {
      "15": {
        "text": 1
      }
    },
    "positions": {
      "15": [
        615
      ]
    },
    "idf": 2.5902671654458267,
    "total_frequency": 1
  },
  "3103": {
    "document_frequencies": {
      "18": 1.0
    },
    "field_frequencies": {
      "18": {
        "text": 1
      }
    },
    "positions": {
      "18": [
        826
      ]
    },
    "idf": 2.5902671654458267,
    "total_frequency": 1
  }
}