{
  "227": {
    "document_frequencies": {
      "0": 4.0,
      "4": 5.0,
      "11": 4.0
    },
    "field_frequencies": {
      "0": {
        "text": 4
      },
      "4": {
        "text": 5
      },
      "11": {
        "text": 4
      }
    },
    "positions": {
      "0": [
        6,
        12,
        483,
        523
      ],
      "4": [
        32,
        44,
        74,
        152,
        175
      ],
      "11": [
        12,
        100,
        240,
        267
      ]
    },
    "idf": 1.742969305058623,
    "total_frequency": 13
  },
  "483": {
    "document_frequencies": {
      "1": 2.0,
      "8": 1.0,
      "12": 1.0
    },
    "field_frequencies": {
      "1": {
        "text": 2
      },
      "8": {
        "text": 1
      },
      "12": {
        "text": 1
      }
    },
    "positions": {
      "1": [
        49,
        172
      ],
      "8": [
        375
      ],
      "12": [
        382
      ]
    },
    "idf": 1.742969305058623,
    "total_frequency": 4
  },
  "739": {
    "document_frequencies": {
      "3": 2.0,
      "8": 1.0,
      "10": 2.0
    },
    "field_frequencies": {
      "3": {
        "text": 2
      },
      "8": {
        "text": 1
      },
      "10": {
        "text": 2
      }
    },
    "positions": {
      "3": [
        151,
        157
      ],
      "8": [
        402
      ],
      "10": [
        519,
        535
      ]
    },
    "idf": 1.742969305058623,
    "total_frequency": 5
  },
  "995": {
    "document_frequencies": {
      "5": 3.0,
      "7": 5.0,
      "8": 1.0,
      "10": 1.0,
      "12": 1.0,
      "15": 1.0,
      "18": 6.0
    },
    "field_frequencies": {
      "5": {
        "text": 3
      },
      "7": {
        "text": 5
      },
      "8": {
        "text": 1
      },
      "10": {
        "text": 1
      },
      "12": {
        "text": 1
      },
      "15": {
        "text": 1
      },
      "18": {
        "text": 6
      }
    },
    "positions": {
      "5": [
        69,
        333,
        440
      ],
      "7": [
        180,
        383,
        423,
        534,
        671
      ],
      "8": [
        296
      ],
      "10": [
        65
      ],
      "12": [
        552
      ],
      "15": [
        475
      ],
      "18": [
        275,
        335,
        383,
        627,
        653,
        748
      ]
    },
    "idf": 0.9808292530117262,
    "total_frequency": 18
  },
  "1251": {
    "document_frequencies": {
      "6": 1.0,
      "7": 1.0,
      "13": 1.0
    },
    "field_frequencies": {
      "6": {
        "text": 1
      },
      "7": {
        "text": 1
      },
      "13": {
        "text": 1
      }
    },
    "positions": {
      "6": [
        476
      ],
      "7": [
        116
      ],
      "13": [
        51
      ]
    },
    "idf": 1.742969305058623,
    "total_frequency": 3
  },
  "1507": {
    "document_frequencies": {
      "7": 1.0
    },
    "field_frequencies": {
      "7": {
        "text": 1
      }
    },
    "positions": {
      "7": [
        81
      ]
    },
    "idf": 2.5902671654458267,
    "total_frequency": 1
  },
  "1763": {
    "document_frequencies": {
      "8": 1.0,
      "12": 3.0
    },
    "field_frequencies": {
      "8": {
        "text": 1
      },
      "12": {
        "text": 3
      }
    },
    "positions": {
      "8": [
        325
      ],
      "12": [
        597,
        600,
        613
      ]
    },
    "idf": 2.0794415416798357,
    "total_frequency": 4
  },
  "2019": {
    "document_frequencies": {
      "9": 1.0
    },
    "field_frequencies": {
      "9": {
        "text": 1
      }
    },
    "positions": {
      "9": [
        8
      ]
    },
    "idf": 2.5902671654458267,
    "total_frequency": 1
  },
  "2275": {
    "document_frequencies": {
      "11": 1.0
    },
    "field_frequencies": {
      "11": {
        "text": 1
      }
    },
    "positions": {
      "11": [
        256
      ]
    },
    "idf": 2.5902671654458267,
    "total_frequency": 1
  },
  "2531": {
    "document_frequencies": {
      "12": 1.0
    },
    "field_frequencies": {
      "12": {
        "text": 1
      }
    },
    "positions": {
      "12": [
        370
      ]
    },
    "idf": 2.5902671654458267,
    "total_frequency": 1
  },
  "2787": {
    "document_frequencies": {
      "15": 5.0,
      "18": 1.0
    },
    "field_frequencies": {
      "15": {
        "text": 5
      },
      "18": {
        "text": 1
      }
    },
    "positions": {
      "15": [
        279,
        385,
        400,
        410,
        431
      ],
      "18": [
        102
      ]
    },
    "idf": 2.0794415416798357,
    "total_frequency": 6
  },
  "3043": {
    "document_frequencies": {
      "18": 3.0
    },
    "field_frequencies": {
      "18": {
        "text": 3
      }
    },
    "positions": {
      "18": [
        894,
        897,
        902
      ]
    },
    "idf": 2.5902671654458267,
    "total_frequency": 3
  }
}